teleclass/__init__.py
teleclass/classifiers/similarity_classifier.py
teleclass/core/__init__.py
teleclass/core/builder.py
teleclass/core/cache.py
teleclass/core/document_loader.py
teleclass/core/embeddings.py
teleclass/core/models/__init__.py
teleclass/core/models/enrichment_models.py
teleclass/core/models/models.py
teleclass/core/taxonomy_manager.py
teleclass/core/teleclass.py
teleclass/enrichers/__init__.py
teleclass/enrichers/corpus_enricher.py
teleclass/enrichers/llm_enricher.py
teleclass/utils/__init__.py
teleclass_classifier-0.1.0.dist-info/METADATA
teleclass_classifier-0.1.0.dist-info/WHEEL
teleclass_classifier-0.1.0.dist-info/RECORD
