Metadata-Version: 2.3
Name: teleclass-classifier
Version: 0.1.0
Summary: TELEClass Classifier is a simplified TELEClass implementation to classify incoming IoT data sources in SensorThings API format into pre-defined hierarchial classification schema for urban sensors.
License: MIT
Author: Jeffrey Limnardy
Author-email: jeffreylimnardy@yahoo.com
Requires-Python: >=3.11,<4.0
Classifier: License :: OSI Approved :: MIT License
Classifier: Programming Language :: Python :: 3
Classifier: Programming Language :: Python :: 3.11
Classifier: Programming Language :: Python :: 3.12
Classifier: Programming Language :: Python :: 3.13
Requires-Dist: keybert (>=0.8.5,<0.9.0)
Requires-Dist: networkx (>=3.4.2,<4.0.0)
Requires-Dist: numpy (>=2.2.1,<3.0.0)
Requires-Dist: ollama (>=0.4.5,<0.5.0)
Requires-Dist: pydantic (>=2.10.4,<3.0.0)
Requires-Dist: rank-bm25 (>=0.2.2,<0.3.0)
Requires-Dist: sentence-transformers (>=3.3.1,<4.0.0)
Requires-Dist: torch (>=2.5.1,<3.0.0)
Requires-Dist: transformers (>=4.47.1,<5.0.0)
Requires-Dist: yake (>=0.4.8,<0.5.0)
